{
  "videos": [
    {
      "id": "african-cuisine",
      "video_path": "./assets/video/the-rise-and-fall-of-empires-in-africa.mp4",
      "still_path": "./assets/img/the-rise-and-fall-of-empires-in-africa.png",
      "title": "African Cuisine: Food Activism in NC",
      "description": "Food activist Njathi Kabui argues for why food should be an integral part of the museum experience.",
      "attribution": ""
    },
    {
      "id": "palm-sangria",
      "video_path": "./assets/video/the-rise-and-fall-of-empires-in-africa.mp4",
      "still_path": "./assets/img/the-rise-and-fall-of-empires-in-africa.png",
      "title": "Palm Sangria Inspired by <i>Lines That Link Humanity</i>",
      "description": "Mixologist Ernest Gantz creates a drink inspired by <i>Lines That Link Humanity</i> and Ghanan culture.",
      "attribution": ""
    },
    {
      "id": "magdalene-odundo",
      "video_path": "./assets/video/the-rise-and-fall-of-empires-in-africa.mp4",
      "still_path": "./assets/img/the-rise-and-fall-of-empires-in-africa.png",
      "title": "Get to Know Ceramic Artist Magdalene Odundo (UK, Kenya)",
      "description": "Odundo talks about how her travels have encouraged her to make art and learn about cultures.",
      "attribution": ""
    },
    {
      "id": "ledelle-moe",
      "video_path": "./assets/video/the-rise-and-fall-of-empires-in-africa.mp4",
      "still_path": "./assets/img/ledelle-moe-1.png",
      "title": "Get to Know Sculptor Ledelle Moe (South Africa)",
      "description": "Moe discusses the challenges she has faced as an artist.",
      "attribution": ""
    },
    {
      "id": "lamidi-fakeye",
      "video_path": "./assets/video/the-rise-and-fall-of-empires-in-africa.mp4",
      "still_path": "./assets/img/lamidi-fakeye-1.png",
      "title": "Get to Know Carver Lamidi Fakeye (Nigeria)",
      "description": "Learn about how Fakeye's artwork is a bridge between the past, present, and future.",
      "attribution": ""
    }
  ]
}
